{
  "timestamp": "2026-05-29T17:42:33.517Z",
  "microfrontends": {
    "@linm/erp-analytics": {
      "url": "/linm-erp-analytics.9c3ac79a.js",
      "filename": "linm-erp-analytics.9c3ac79a.js",
      "version": "1.0.0-dev.5",
      "timebuild": "2026-05-29T17:32:44.612Z",
      "routes": [
        "baocao"
      ]
    },
    "@linm/erp-finance": {
      "url": "/linm-erp-finance.63af92af.js",
      "filename": "linm-erp-finance.63af92af.js",
      "version": "1.0.0-dev.5",
      "timebuild": "2026-05-29T17:32:50.068Z",
      "routes": [
        "kt",
        "gt",
        "tscd"
      ]
    },
    "@linm/erp-sales": {
      "url": "/linm-erp-sales.9c1ba709.js",
      "filename": "linm-erp-sales.9c1ba709.js",
      "version": "1.0.0-dev.5",
      "timebuild": "2026-05-29T17:33:03.320Z",
      "routes": [
        "bh"
      ]
    },
    "@linm/erp-mes": {
      "url": "/linm-erp-mes.50e25f1d.js",
      "filename": "linm-erp-mes.50e25f1d.js",
      "version": "1.0.0-dev.5",
      "timebuild": "2026-05-29T17:32:57.580Z",
      "routes": [
        "sx"
      ]
    },
    "@linm/erp-master": {
      "url": "/linm-erp-master.25f14eeb.js",
      "filename": "linm-erp-master.25f14eeb.js",
      "version": "1.0.0-dev.7",
      "timebuild": "2026-05-29T17:33:05.946Z",
      "routes": [
        "dm",
        "system"
      ]
    },
    "@linm/admin": {
      "url": "/linm-admin.cb965016.js",
      "filename": "linm-admin.cb965016.js",
      "version": "1.0.3-dev.21",
      "timebuild": "2026-05-29T17:32:07.411Z",
      "routes": [
        "admin"
      ]
    },
    "@linm/dashboard": {
      "url": "/linm-dashboard.a1bf8f98.js",
      "filename": "linm-dashboard.a1bf8f98.js",
      "version": "1.0.0-dev.15",
      "timebuild": "2026-05-29T17:31:53.148Z",
      "routes": [
        "dashboard"
      ]
    },
    "@linm/erp-master-parcel": {
      "url": "/linm-erp-master-parcel.d3f82b8d.js",
      "filename": "linm-erp-master-parcel.d3f82b8d.js",
      "version": "unknown",
      "timebuild": "2026-05-29T15:24:43.294Z"
    },
    "@linm/message": {
      "url": "/linm-message.js",
      "filename": "linm-message.js",
      "version": "1.0.0-dev.16",
      "timebuild": "2026-05-29T17:32:12.003Z"
    },
    "@linm/nav": {
      "url": "/linm-nav.8f7246fd.js",
      "filename": "linm-nav.8f7246fd.js",
      "version": "1.0.5-dev.25",
      "timebuild": "2026-05-29T17:42:33.520Z"
    },
    "@linm/root-config": {
      "url": "/linm-root-config.js",
      "filename": "linm-root-config.js",
      "version": "1.0.30-dev.17",
      "timebuild": "2026-05-29T16:55:05.045Z"
    },
    "@linm/web-home": {
      "url": "/linm-web-home.ae17c68a.js",
      "filename": "linm-web-home.ae17c68a.js",
      "version": "1.0.6-dev.24",
      "timebuild": "2026-05-29T17:32:09.369Z",
      "routes": [
        "login",
        "settings",
        "notifications",
        "messages",
        "help",
        "faq",
        "contact",
        "install-guide",
        "notification-guide"
      ],
      "default": true
    }
  },
  "publicUrl": ""
}
