{
  "timestamp": "2026-05-29T11:43:26.026Z",
  "microfrontends": {
    "@linm/admin": {
      "url": "/linm-admin.3c3a7f6b.js",
      "filename": "linm-admin.3c3a7f6b.js",
      "version": "1.0.3-dev.12",
      "timebuild": "2026-05-29T10:42:43.079Z"
    },
    "@linm/dashboard": {
      "url": "/linm-dashboard.4c72d835.js",
      "filename": "linm-dashboard.4c72d835.js",
      "version": "1.0.0-dev.6",
      "timebuild": "2026-05-29T10:36:56.274Z"
    },
    "@linm/message": {
      "url": "/linm-message.js",
      "filename": "linm-message.js",
      "version": "1.0.0-dev.7",
      "timebuild": "2026-05-29T10:37:13.183Z"
    },
    "@linm/nav": {
      "url": "/linm-nav.12a582da.js",
      "filename": "linm-nav.12a582da.js",
      "version": "1.0.5-dev.13",
      "timebuild": "2026-05-29T11:43:26.004Z"
    },
    "@linm/root-config": {
      "url": "/linm-root-config.js",
      "filename": "linm-root-config.js",
      "version": "1.0.30-dev.10",
      "timebuild": "2026-05-29T10:36:39.076Z"
    },
    "@linm/web-home": {
      "url": "/linm-web-home.1269c0d8.js",
      "filename": "linm-web-home.1269c0d8.js",
      "version": "1.0.6-dev.15",
      "timebuild": "2026-05-29T10:49:59.698Z"
    }
  }
}
